AUTHORS.rst
CONTRIBUTING.rst
HISTORY.rst
LICENSE
MANIFEST.in
README.rst
setup.cfg
setup.py
dgim/__init__.py
dgim/dgim.py
dgim/utils.py
dgim.egg-info/PKG-INFO
dgim.egg-info/SOURCES.txt
dgim.egg-info/dependency_links.txt
dgim.egg-info/not-zip-safe
dgim.egg-info/top_level.txt
docs/Makefile
docs/classes.rst
docs/conf.py
docs/history.rst
docs/index.rst
docs/make.bat
docs/readme.rst
tests/.test_dgim.py.swp
tests/.test_dgim_quality.py.swp
tests/__init__.py
tests/test_dgim.py
tests/test_dgim_quality.py