Metadata-Version: 1.1
Name: dgim
Version: 0.2.0
Summary: Python implementation of the dgim algorithm: Compact datastructure to estimate the number of "True" in the last N elements of a boolean stream.
Home-page: https://github.com/simondolle/dgim
Author: Simon Dollé
Author-email: simon.dolle@gmail.com
License: BSD
Keywords: dgim
Platform: UNKNOWN
Classifier: Development Status :: 2 - Pre-Alpha
Classifier: Intended Audience :: Developers
Classifier: License :: OSI Approved :: BSD License
Classifier: Natural Language :: English
Classifier: Programming Language :: Python :: 2
Classifier: Programming Language :: Python :: 2.6
Classifier: Programming Language :: Python :: 2.7
Classifier: Programming Language :: Python :: 3
Classifier: Programming Language :: Python :: 3.3
Classifier: Programming Language :: Python :: 3.4
